.travis.yml
MANIFEST.in
NOTICE.txt
README.rst
bootstrap.py
buildout.cfg
edrn.rdf.sublime-project
setup.py
travis.cfg
docs/HISTORY.txt
docs/INSTALL.txt
docs/LICENSE.txt
docs/Protocols.graffle
edrn/__init__.py
edrn.rdf.egg-info/PKG-INFO
edrn.rdf.egg-info/SOURCES.txt
edrn.rdf.egg-info/dependency_links.txt
edrn.rdf.egg-info/entry_points.txt
edrn.rdf.egg-info/namespace_packages.txt
edrn.rdf.egg-info/not-zip-safe
edrn.rdf.egg-info/requires.txt
edrn.rdf.egg-info/top_level.txt
edrn/rdf/README.rst
edrn/rdf/__init__.py
edrn/rdf/biomutardfgenerator.py
edrn/rdf/configure.zcml
edrn/rdf/dmcccommitteerdfgenerator.py
edrn/rdf/dmccprotocolrdfgenerator.py
edrn/rdf/dmccprotocolrdfgenerator.txt
edrn/rdf/edrnlabcasrdfgenerator.py
edrn/rdf/exceptions.py
edrn/rdf/interfaces.py
edrn/rdf/literalpredicatehandler.py
edrn/rdf/multiliteralpredicatehandler.py
edrn/rdf/nullrdfgenerator.py
edrn/rdf/predicatehandler.py
edrn/rdf/rdfgenerator.py
edrn/rdf/rdfsource.py
edrn/rdf/rdfupdater.py
edrn/rdf/referencepredicatehandler.py
edrn/rdf/setuphandlers.py
edrn/rdf/simpledmccrdfgenerator.py
edrn/rdf/siterdfupdater.py
edrn/rdf/testing.py
edrn/rdf/upgrades.py
edrn/rdf/upgrades.zcml
edrn/rdf/utils.py
edrn/rdf/profiles/default/edrn.rdf.marker.txt
edrn/rdf/profiles/default/metadata.xml
edrn/rdf/profiles/default/types.xml
edrn/rdf/profiles/default/types/edrn.rdf.biomutardfgenerator.xml
edrn/rdf/profiles/default/types/edrn.rdf.dmcccommitteerdfgenerator.xml
edrn/rdf/profiles/default/types/edrn.rdf.dmccprotocolrdfgenerator.xml
edrn/rdf/profiles/default/types/edrn.rdf.edrnlabcasrdfgenerator.xml
edrn/rdf/profiles/default/types/edrn.rdf.literalpredicatehandler.xml
edrn/rdf/profiles/default/types/edrn.rdf.multiliteralpredicatehandler.xml
edrn/rdf/profiles/default/types/edrn.rdf.nullrdfgenerator.xml
edrn/rdf/profiles/default/types/edrn.rdf.rdfsource.xml
edrn/rdf/profiles/default/types/edrn.rdf.referencepredicatehandler.xml
edrn/rdf/profiles/default/types/edrn.rdf.simpledmccrdfgenerator.xml
edrn/rdf/siterdfupdater_templates/siterdfupdater.pt
edrn/rdf/static/dmcccommitteerdfgenerator.png
edrn/rdf/static/dmccprotocolrdfgenerator.png
edrn/rdf/static/literalpredicatehandler.png
edrn/rdf/static/multiliteralpredicatehandler.png
edrn/rdf/static/nullrdfgenerator.png
