Metadata-Version: 2.1
Name: edrn.rdf
Version: 1.3.7
Summary: EDRN RDF Server
Home-page: https://github.com/EDRN/edrn.rdf
Author: Sean Kelly
Author-email: sean.kelly@jpl.nasa.gov
Maintainer: Sean Kelly
Maintainer-email: sean.kelly@jpl.nasa.gov
License: ALv2
Keywords: rdf web zope plone cancer bioinformatics detection informatics edrn
Platform: UNKNOWN
Classifier: Development Status :: 4 - Beta
Classifier: Environment :: Web Environment
Classifier: Framework :: Plone
Classifier: Intended Audience :: Healthcare Industry
Classifier: Intended Audience :: Science/Research
Classifier: License :: OSI Approved :: Apache Software License
Classifier: Operating System :: OS Independent
Classifier: Programming Language :: Python
Classifier: Topic :: Internet :: WWW/HTTP
Classifier: Topic :: Scientific/Engineering :: Bio-Informatics
Classifier: Topic :: Software Development :: Libraries :: Python Modules
Provides-Extra: test
